npzviewer/__init__.py
npzviewer/__main__.py
npzviewer/npzviewer.py
npzviewer-0.1.1.dist-info/LICENSE
npzviewer-0.1.1.dist-info/METADATA
npzviewer-0.1.1.dist-info/WHEEL
npzviewer-0.1.1.dist-info/entry_points.txt
npzviewer-0.1.1.dist-info/top_level.txt
npzviewer-0.1.1.dist-info/RECORD
