Metadata-Version: 2.1
Name: npzviewer
Version: 0.1.1
Summary: A simple PyQt5 .npz file viewer.
Home-page: https://github.com/ericoporto/npzviewer
Author: Erico Vieira Porto
Author-email: eri0onpm@gmail.com
License: GPLv2
Download-URL: https://github.com/ericoporto/npzviewer/tarball/0.1.1
Keywords: numpy development
Platform: UNKNOWN
Classifier: Development Status :: 3 - Alpha
Classifier: Intended Audience :: Developers
Classifier: License :: OSI Approved :: GNU General Public License v2 (GPLv2)
Classifier: Programming Language :: Python :: 3.5
Requires-Dist: numpy
Requires-Dist: pyqt5
